{
    "chinese": {
        "keys": {
            "checkboxAll": "全部",
            "checkboxChecked": "已检查",
            "checkboxIndeterminate": "不定",
            "checkboxUnchecked": "未检查",
            "columnAdd": "添加栏",
            "columnAddDescription": "添加代码/描述列",
            "columnColumns": "列",
            "columnHide": "隐藏栏",
            "columnMerge": "合并列",
            "columnNoFormula": "这些列没有可用的公式",
            "columnNonNumerical": "这些列不是数字的",
            "columnNonNumericalInTable": "此表中不存在数字列",
            "columnSwap": "交换",
            "dashboardDimension": "方面",
            "dashboardLoaded": "已加载",
            "dashboardReset": "重置",
            "dashboardSave": "节省",
            "dashboardVertical": "垂直的",
            "debugAutoprint": "切换自动打印",
            "debugClear": "清除小部件",
            "debugDLAll": "全部",
            "debugDLProps": "下载组件道具",
            "debugDLPropsComp": "下载组件道具",
            "debugDump": "转储存储的日志",
            "debugLanguageChanger": "设置语言",
            "debugLocaleChanger": "設置語言環境",
            "debugLogLimit": "设置日志限制",
            "debugMagicBox": "切换kup-magic-box",
            "debugOff": "关闭调试",
            "debugPrint": "打印已存储的日志",
            "debugThemeChanger": "设置主题",
            "densityDense": "稠密",
            "densityLabel": "行密度",
            "densityMedium": "中等的",
            "densityWide": "宽的",
            "fontsizeBig": "大的",
            "fontsizeLabel": "字体大小",
            "fontsizeMedium": "中等的",
            "fontsizeSmall": "小的",
            "genericAbort": "取消",
            "genericAddNew": "添新",
            "genericApply": "申请",
            "genericBack": "背部",
            "genericCollapse": "坍塌",
            "genericConfirm": "确认",
            "genericConfirmDelete": "你确认取消了吗?",
            "genericConfirmDeleteXRows": "删除（{0}）行?",
            "genericDay": "日",
            "genericDragAndDrop": "拖放",
            "genericDropYourData": "将您的数据放在这里",
            "genericEditable": "可编辑的",
            "genericEditableField": "该字段可以编辑",
            "genericEmptyData": "空数据",
            "genericEmptyObject": "空对象",
            "genericExpand": "扩张",
            "genericExperimentalFeat": "实验功能",
            "genericFilters": "筛选器",
            "genericInfo": "信息",
            "genericInvalidColor": "颜色无效",
            "genericLayoutNotYetImplemented": "布局尚未实施",
            "genericList": "列表",
            "genericLoadMoreData": "加载更多数据",
            "genericMenu": "画面",
            "genericMerge": "合并",
            "genericMonth": "月",
            "genericMove": "移动",
            "genericNext": "下一个",
            "genericNo": "不",
            "genericOpenInNewTab": "在新标签页中打开",
            "genericOpenInNewWindow": "在新窗口中打开",
            "genericOpenNavigationMenu": "打开导航菜单",
            "genericOptions": "选项",
            "genericPrevious": "以前的",
            "genericRemoveFilters": "删除过滤器",
            "genericSettings": "设置",
            "genericShowRowOptions": "显示行选项",
            "genericShowTooltipInfo": "显示工具提示信息",
            "genericSortBy": "排序方式",
            "genericSwap": "隐藏栏",
            "genericToday": "今天",
            "genericToggle": "切换",
            "genericTop": "最佳",
            "genericTotalsTable": "总计表",
            "genericTransposeData": "转置数据",
            "genericViewAs": "查看为",
            "genericWeek": "星期",
            "genericYes": "是的",
            "gridColumn": "柱子",
            "gridComplete": "完全的",
            "gridLabel": "网格类型",
            "gridNone": "没有任何",
            "gridRow": "排",
            "groupingDisable": "禁用分组",
            "groupingEnable": "启用分组",
            "groupingGroups": "团体",
            "pagePage": "页",
            "pageTotal": "总页数",
            "rowDetail": "行详细信息",
            "rowEditableKey": "可编辑的记录键",
            "rowKey": "记录键",
            "rowNext": "下一行",
            "rowPrevious": "上一行",
            "rowRendered": "渲染的行",
            "rowRows": "行数",
            "rowSelected": "选定的行",
            "rowTotal": "总行数",
            "searchFrom": "从",
            "searchSearch": "搜索",
            "searchTo": "至",
            "totalsAverage": "平均数",
            "totalsCalculate": "计算",
            "totalsCancel": "取消",
            "totalsCount": "数数",
            "totalsDifference": "不同之处",
            "totalsDistinct": "清楚的",
            "totalsFormula": "公式",
            "totalsMaximum": "最大",
            "totalsMinimum": "最低限度",
            "totalsProduct": "产物",
            "totalsSum": "和"
        }
    },
    "english": {
        "keys": {
            "checkboxAll": "All",
            "checkboxChecked": "Checked",
            "checkboxIndeterminate": "Indeterminate",
            "checkboxUnchecked": "Unchecked",
            "columnAdd": "Add column",
            "columnAddDescription": "Add code/description column",
            "columnColumns": "Columns",
            "columnHide": "Hide column",
            "columnMerge": "Merge columns",
            "columnNoFormula": "No formulas available for these columns.",
            "columnNonNumerical": "These columns are not numerical.",
            "columnNonNumericalInTable": "No numerical columns exist in this table.",
            "columnSwap": "Swap columns",
            "dashboardDimension": "Dimension",
            "dashboardLoaded": "Loaded",
            "dashboardReset": "Reset",
            "dashboardSave": "Save",
            "dashboardVertical": "Vertical",
            "debugAutoprint": "Toggle automatic print",
            "debugClear": "Clear widget",
            "debugDLAll": "All",
            "debugDLProps": "Download components props",
            "debugDLPropsComp": "Download component props",
            "debugDump": "Dump stored logs",
            "debugLanguageChanger": "Set language",
            "debugLocaleChanger": "Set locale",
            "debugLogLimit": "Set log limit",
            "debugMagicBox": "Toggle kup-magic-box",
            "debugOff": "Turn off debug",
            "debugPrint": "Print logs stored",
            "debugThemeChanger": "Set theme",
            "densityDense": "Dense",
            "densityLabel": "Row density",
            "densityMedium": "Medium",
            "densityWide": "Wide",
            "fontsizeBig": "Big",
            "fontsizeLabel": "Font size",
            "fontsizeMedium": "Medium",
            "fontsizeSmall": "Small",
            "genericAbort": "Cancel",
            "genericAddNew": "Add new",
            "genericApply": "Apply",
            "genericBack": "Back",
            "genericCollapse": "Collapse",
            "genericConfirm": "Confirm",
            "genericConfirmDelete": "Do you confirm the cancellation?",
            "genericConfirmDeleteXRows": "Delete ({0}) rows?",
            "genericDay": "Day",
            "genericDragAndDrop": "Drag and drop",
            "genericDropYourData": "Drop your data here",
            "genericEditable": "Editable",
            "genericEditableField": "This field can be edited",
            "genericEmptyData": "Empty data.",
            "genericEmptyObject": "Empty object",
            "genericExpand": "Expand",
            "genericExperimentalFeat": "Experimental feature",
            "genericFilters": "Filters",
            "genericInfo": "Info",
            "genericInvalidColor": "Invalid color",
            "genericLayoutNotYetImplemented": "Layout not yet implemented",
            "genericList": "List",
            "genericLoadMoreData": "Load more data",
            "genericMenu": "Menu",
            "genericMerge": "Merge",
            "genericMonth": "Month",
            "genericMove": "Move",
            "genericNext": "Next",
            "genericNo": "No",
            "genericOpenInNewTab": "Open in new tab",
            "genericOpenInNewWindow": "Open in new window",
            "genericOpenNavigationMenu": "Open navigation menu",
            "genericOptions": "Options",
            "genericPrevious": "Previous",
            "genericRemoveFilters": "Remove filters",
            "genericSettings": "Settings",
            "genericShowRowOptions": "Show row options",
            "genericShowTooltipInfo": "Show tooltip info",
            "genericSortBy": "Sort by",
            "genericSwap": "Swap",
            "genericToday": "Today",
            "genericToggle": "Toggle",
            "genericTop": "Top",
            "genericTotalsTable": "Totals table",
            "genericTransposeData": "Transpose data",
            "genericViewAs": "View as",
            "genericWeek": "Week",
            "genericYes": "Yes",
            "gridColumn": "Column",
            "gridComplete": "Complete",
            "gridLabel": "Grid type",
            "gridNone": "None",
            "gridRow": "Row",
            "groupingDisable": "Disable grouping",
            "groupingEnable": "Enable grouping",
            "groupingGroups": "Group",
            "pagePage": "Page",
            "pageTotal": "Total",
            "rowDetail": "Row detail",
            "rowEditableKey": "Editable record key",
            "rowKey": "Record key",
            "rowNext": "Next row",
            "rowPrevious": "Previous row",
            "rowRendered": "Rendered rows",
            "rowRows": "Rows",
            "rowSelected": "Selected rows",
            "rowTotal": "Total rows",
            "searchFrom": "From",
            "searchSearch": "Search",
            "searchTo": "To",
            "totalsAverage": "Average",
            "totalsCalculate": "Calculate",
            "totalsCancel": "Cancel",
            "totalsCount": "Count",
            "totalsDifference": "Difference",
            "totalsDistinct": "Distinct",
            "totalsFormula": "Formula",
            "totalsMaximum": "Maximum",
            "totalsMinimum": "Minimum",
            "totalsProduct": "Product",
            "totalsSum": "Sum"
        }
    },
    "french": {
        "keys": {
            "checkboxAll": "Tout",
            "checkboxChecked": "Vérifié",
            "checkboxIndeterminate": "Indéterminé",
            "checkboxUnchecked": "Non coché",
            "columnAdd": "Ajouter une colonne",
            "columnAddDescription": "Ajouter une colonne code / description",
            "columnColumns": "Colonnes",
            "columnHide": "Masquer la colonne",
            "columnMerge": "Fusionner des colonnes",
            "columnNoFormula": "Aucune formule disponible pour ces colonnes.",
            "columnNonNumerical": "Ces colonnes ne sont pas numériques.",
            "columnNonNumericalInTable": "Aucune colonne numérique n'existe dans ce tableau.",
            "columnSwap": "Permuter les colonnes",
            "dashboardDimension": "Dimension",
            "dashboardLoaded": "Chargé",
            "dashboardReset": "Réinitialiser",
            "dashboardSave": "Enregistrer",
            "dashboardVertical": "Vertical",
            "debugAutoprint": "Activer l'impression automatique",
            "debugClear": "Effacer le widget",
            "debugDLAll": "Tout",
            "debugDLProps": "Télécharger les accessoires des composants",
            "debugDLPropsComp": "Télécharger les accessoires des composants",
            "debugDump": "Vider les journaux stockés",
            "debugLanguageChanger": "Définir la langue",
            "debugLocaleChanger": "Définir les paramètres régionaux",
            "debugLogLimit": "Définir la limite du journal",
            "debugMagicBox": "Activer / désactiver kup-magic-box",
            "debugOff": "Désactiver le débogage",
            "debugPrint": "Imprimer les journaux stockés",
            "debugThemeChanger": "Définir le thème",
            "densityDense": "Dense",
            "densityLabel": "Densité des rangs",
            "densityMedium": "Moyen",
            "densityWide": "Large",
            "fontsizeBig": "Gros",
            "fontsizeLabel": "Taille de police",
            "fontsizeMedium": "Moyen",
            "fontsizeSmall": "Petit",
            "genericAbort": "Annuler",
            "genericAddNew": "Ajouter un nouveau",
            "genericApply": "Appliquer",
            "genericBack": "Arrière",
            "genericCollapse": "Effondrer",
            "genericConfirm": "Confirmer",
            "genericConfirmDelete": "Confirmez-vous l'annulation?",
            "genericConfirmDeleteXRows": "Supprimer ({0}) lignes?",
            "genericDay": "Jour",
            "genericDragAndDrop": "Glisser-déposer",
            "genericDropYourData": "Déposez vos données ici",
            "genericEditable": "Modifiable",
            "genericEditableField": "Ce champ peut être édité",
            "genericEmptyData": "Données vides",
            "genericEmptyObject": "Objet vides",
            "genericExpand": "Étendre",
            "genericExperimentalFeat": "Fonctionnalité expérimentale",
            "genericFilters": "Filtres",
            "genericInfo": "Info",
            "genericInvalidColor": "Couleur invalide",
            "genericLayoutNotYetImplemented": "Mise en page pas encore implémentée",
            "genericList": "Lister",
            "genericLoadMoreData": "Charger plus de données",
            "genericMenu": "Menu",
            "genericMerge": "Fusionner",
            "genericMonth": "Mois",
            "genericMove": "Se déplacer",
            "genericNext": "Prochain",
            "genericNo": "Non",
            "genericOpenInNewTab": "Ouvrir dans un nouvel onglet",
            "genericOpenInNewWindow": "Ouvrir dans une nouvelle fenêtre",
            "genericOpenNavigationMenu": "Ouvrir le menu de navigation",
            "genericOptions": "Options",
            "genericPrevious": "Précédent",
            "genericRemoveFilters": "Supprimer les filtres",
            "genericSettings": "Paramètres",
            "genericShowRowOptions": "Afficher les options de ligne",
            "genericShowTooltipInfo": "Afficher les informations de l'info-bulle",
            "genericSortBy": "Trier par",
            "genericSwap": "Échanger",
            "genericToday": "Aujourd'hui",
            "genericToggle": "Basculer",
            "genericTop": "Haut",
            "genericTotalsTable": "Tableau des totaux",
            "genericTransposeData": "Transposer les données",
            "genericViewAs": "Voir comme",
            "genericWeek": "La semaine",
            "genericYes": "Oui",
            "gridColumn": "Colonne",
            "gridComplete": "Compléte",
            "gridLabel": "Type de grille",
            "gridNone": "Rien",
            "gridRow": "Ligne",
            "groupingDisable": "Désactiver le regroupement",
            "groupingEnable": "Activer le regroupement",
            "groupingGroups": "Groupe",
            "pagePage": "Page",
            "pageTotal": "Pages totales",
            "rowDetail": "Détail de la ligne",
            "rowEditableKey": "Clé d'enregistrement modifiable",
            "rowKey": "Clé d'enregistrement",
            "rowNext": "Ligne suivante",
            "rowPrevious": "Ligne précédente",
            "rowRendered": "Lignes rendues",
            "rowRows": "Lignes",
            "rowSelected": "Lignes sélectionnées",
            "rowTotal": "Total des lignes",
            "searchFrom": "De",
            "searchSearch": "Rechercher",
            "searchTo": "À",
            "totalsAverage": "Moyenne",
            "totalsCalculate": "Calculer",
            "totalsCancel": "Annuler",
            "totalsCount": "Compter",
            "totalsDifference": "Différence",
            "totalsDistinct": "Distinct",
            "totalsFormula": "Formule",
            "totalsMaximum": "Maximum",
            "totalsMinimum": "Minimum",
            "totalsProduct": "Produit",
            "totalsSum": "Somme"
        }
    },
    "italian": {
        "keys": {
            "checkboxAll": "Tutti",
            "checkboxChecked": "Selezionato",
            "checkboxIndeterminate": "Indeterminato",
            "checkboxUnchecked": "Non selezionato",
            "columnAdd": "Aggiungi colonna",
            "columnAddDescription": "Aggiungi colonna codice/descrizione",
            "columnColumns": "Colonne",
            "columnHide": "Nascondi colonna",
            "columnMerge": "Unisci le colonne",
            "columnNoFormula": "Non ci sono formule disponibili per queste colonne.",
            "columnNonNumerical": "Queste colonne non sono numeriche.",
            "columnNonNumericalInTable": "Non esistono colonne numeriche in questa tabella.",
            "columnSwap": "Scambia le colonne",
            "dashboardDimension": "Dimensione",
            "dashboardLoaded": "Caricata",
            "dashboardReset": "Ripristina",
            "dashboardSave": "Salva",
            "dashboardVertical": "Verticale",
            "debugAutoprint": "Attiva stampa automatica logs",
            "debugClear": "Pulisci widget",
            "debugDLAll": "Tutto",
            "debugDLProps": "Scarica props componenti",
            "debugDLPropsComp": "Scarica props del componente",
            "debugDump": "Svuota cache dei logs",
            "debugLanguageChanger": "Cambia lingua",
            "debugLocaleChanger": "Cambia localizzazione",
            "debugLogLimit": "Imposta limite log",
            "debugMagicBox": "Attiva kup-magic-box",
            "debugOff": "Disattiva debug",
            "debugPrint": "Stampa logs immagazzinati",
            "debugThemeChanger": "Cambia tema",
            "densityDense": "Densa",
            "densityLabel": "Densità righe",
            "densityMedium": "Media",
            "densityWide": "Ampia",
            "fontsizeBig": "Grande",
            "fontsizeLabel": "Dimensione caratteri",
            "fontsizeMedium": "Media",
            "fontsizeSmall": "Piccola",
            "genericAbort": "Annulla",
            "genericAddNew": "Aggiungi nuovo",
            "genericApply": "Applica",
            "genericBack": "Indietro",
            "genericCollapse": "Chiudi",
            "genericConfirm": "Conferma",
            "genericConfirmDelete": "Confermi la cancellazione?",
            "genericConfirmDeleteXRows": "Eliminare ({0}) righe?",
            "genericDay": "Giorno",
            "genericDragAndDrop": "Drag & drop",
            "genericDropYourData": "Trascina qui i tuoi dati",
            "genericEditable": "Editabile",
            "genericEditableField": "Questo campo è editabile",
            "genericEmptyData": "Nessun dato da visualizzare.",
            "genericEmptyObject": "Nessun oggetto",
            "genericExpand": "Espandi",
            "genericExperimentalFeat": "Funzionalità sperimentale",
            "genericFilters": "Filtri",
            "genericInfo": "Informazioni",
            "genericInvalidColor": "Colore invalido",
            "genericLayoutNotYetImplemented": "Layout non ancora implementato",
            "genericList": "Lista",
            "genericLoadMoreData": "Carica più dati",
            "genericMenu": "Menu",
            "genericMerge": "Unisci",
            "genericMonth": "Mese",
            "genericMove": "Sposta",
            "genericNext": "Avanti",
            "genericNo": "No",
            "genericOpenInNewTab": "Apri in nuovo tab",
            "genericOpenInNewWindow": "Apri in nuova finestra",
            "genericOpenNavigationMenu": "Apri menu di navigazione",
            "genericOptions": "Opzioni",
            "genericPrevious": "Indietro",
            "genericRemoveFilters": "Rimuovi filtri",
            "genericSettings": "Impostazioni",
            "genericShowRowOptions": "Mostra opzioni di riga",
            "genericShowTooltipInfo": "Mostra informazioni tooltip",
            "genericSortBy": "Ordina per",
            "genericSwap": "Scambia",
            "genericToday": "Oggi",
            "genericToggle": "Attiva",
            "genericTop": "Top",
            "genericTotalsTable": "Tabella dei totali",
            "genericTransposeData": "Trasposizione dati",
            "genericViewAs": "Vedi come",
            "genericWeek": "Settimana",
            "genericYes": "Sì",
            "gridColumn": "Colonna",
            "gridComplete": "Completa",
            "gridLabel": "Tipo di griglia",
            "gridNone": "Nessuna",
            "gridRow": "Riga",
            "groupingDisable": "Disabilita gruppo",
            "groupingEnable": "Abilita gruppo",
            "groupingGroups": "Gruppo",
            "pagePage": "Pagina",
            "pageTotal": "Totale",
            "rowDetail": "Dettaglio riga",
            "rowEditableKey": "Chiave record editabile",
            "rowKey": "Chiave record",
            "rowNext": "Riga successiva",
            "rowPrevious": "Riga precedente",
            "rowRendered": "Righe renderizzate",
            "rowRows": "Righe",
            "rowSelected": "Righe selezionate",
            "rowTotal": "Righe totali",
            "searchFrom": "Da...",
            "searchSearch": "Cerca...",
            "searchTo": "A...",
            "totalsAverage": "Media",
            "totalsCalculate": "Calcola",
            "totalsCancel": "Cancella",
            "totalsCount": "Conta",
            "totalsDifference": "Differenza",
            "totalsDistinct": "Distinct",
            "totalsFormula": "Formula",
            "totalsMinimum": "Minimo",
            "totalsMaximum": "Massimo",
            "totalsProduct": "Prodotto",
            "totalsSum": "Somma"
        },
        "variants": {
            "smeup": {
                "keys": {
                    "columnNonNumericalInTable": "Non esistono colonne numeriche in questa matrice.",
                    "genericEditableField": "Questo OAV è editabile",
                    "genericTotalsTable": "Matrice dei totali",
                    "groupingDisable": "Disabilita raggruppamento",
                    "groupingEnable": "Abilita raggruppamento",
                    "groupingGroups": "Raggruppamento",
                    "rowEditableKey": "K01 (editabile)",
                    "rowKey": "K01"
                }
            }
        }
    },
    "polish": {
        "keys": {
            "checkboxAll": "Wszystko",
            "checkboxChecked": "Sprawdzone",
            "checkboxIndeterminate": "Nieokreślony",
            "checkboxUnchecked": "Niepowstrzymany",
            "columnAdd": "Dodaj kolumnę",
            "columnAddDescription": "Dodaj kolumnę z kodem / opisem",
            "columnColumns": "Kolumny",
            "columnHide": "Ukryj kolumnę",
            "columnMerge": "Scal kolumny",
            "columnNoFormula": "Brak dostępnych formuł dla tych kolumn.",
            "columnNonNumerical": "Te kolumny nie są numeryczne.",
            "columnNonNumericalInTable": "W tej tabeli nie ma kolumn liczbowych.",
            "columnSwap": "Zamień kolumny",
            "dashboardDimension": "Wymiar",
            "dashboardLoaded": "Załadowany",
            "dashboardReset": "Resetowanie",
            "dashboardSave": "Ratować",
            "dashboardVertical": "Pionowy",
            "debugAutoprint": "Przełącz automatyczne drukowanie",
            "debugClear": "Wyczyść widżet",
            "debugDLAll": "Wszystko",
            "debugDLProps": "Pobierz właściwości komponentów",
            "debugDLPropsComp": "Pobierz rekwizyty komponentów",
            "debugDump": "Zrzuć zapisane dzienniki",
            "debugLanguageChanger": "Ustaw język",
            "debugLocaleChanger": "Ustaw język",
            "debugLogLimit": "Ustaw limit logów",
            "debugMagicBox": "Przełącz kup-magic-box",
            "debugOff": "Wyłącz debugowanie",
            "debugPrint": "Drukuj zapisane logi",
            "debugThemeChanger": "Ustaw motyw",
            "densityDense": "Gęsty",
            "densityLabel": "Gęstość rzędów",
            "densityMedium": "Średni",
            "densityWide": "Szeroki",
            "fontsizeBig": "Duży",
            "fontsizeLabel": "Rozmiar czcionki",
            "fontsizeMedium": "Średni",
            "fontsizeSmall": "Mały",
            "genericAbort": "Anulować",
            "genericAddNew": "Dodaj nowe",
            "genericApply": "Zastosować",
            "genericBack": "Plecy",
            "genericCollapse": "Zawalić się",
            "genericConfirm": "Potwierdzać",
            "genericConfirmDelete": "Potwierdzasz odwołanie?",
            "genericConfirmDeleteXRows": "Usunąć ({0}) wiersze?",
            "genericDay": "Dzień",
            "genericDragAndDrop": "Przeciągnij i upuść",
            "genericDropYourData": "Upuść swoje dane tutaj",
            "genericEditable": "Edytowalne",
            "genericEditableField": "To pole można edytować",
            "genericEmptyData": "Puste dane",
            "genericEmptyObject": "Puste obiekt",
            "genericExpand": "Rozszerzać",
            "genericExperimentalFeat": "Funkcja eksperymentalna",
            "genericFilters": "Filtry",
            "genericInfo": "Informacje",
            "genericInvalidColor": "Nieprawidłowy kolor",
            "genericLayoutNotYetImplemented": "Układ nie został jeszcze zaimplementowany",
            "genericList": "Lista",
            "genericLoadMoreData": "Załaduj więcej danych",
            "genericMenu": "Menu",
            "genericMerge": "Łączyć",
            "genericMonth": "Miesiąc",
            "genericMove": "Ruszaj się",
            "genericNext": "Następny",
            "genericNo": "Nie",
            "genericOpenInNewTab": "Otwórz w nowej karcie",
            "genericOpenInNewWindow": "Otworzyć w nowym oknie",
            "genericOpenNavigationMenu": "Otwórz menu nawigacyjne",
            "genericOptions": "Opcje",
            "genericPrevious": "Poprzedni",
            "genericRemoveFilters": "Usuń filtry",
            "genericSettings": "Ustawienia",
            "genericShowRowOptions": "Pokaż opcje wierszy",
            "genericShowTooltipInfo": "Pokaż informacje w podpowiedzi",
            "genericSortBy": "Sortuj według",
            "genericSwap": "Zamiana",
            "genericToday": "Dziś",
            "genericToggle": "Przełącznik",
            "genericTop": "Szczyt",
            "genericTotalsTable": "Tabela sum",
            "genericTransposeData": "Transpozycja danych",
            "genericViewAs": "Wyświetl jako",
            "genericWeek": "Tydzień",
            "genericYes": "TAk",
            "gridColumn": "Kolumna",
            "gridComplete": "Kompletny",
            "gridLabel": "Typ siatki",
            "gridNone": "Żaden",
            "gridRow": "Rząd",
            "groupingDisable": "Wyłącz grupowanie",
            "groupingEnable": "Włącz grupowanie",
            "groupingGroups": "Grupy",
            "pagePage": "Strona",
            "pageTotal": "Wszystkie strony",
            "rowDetail": "Szczegóły rzędu",
            "rowEditableKey": "Edytowalny klucz nagrywania",
            "rowKey": "Klucz nagrywania",
            "rowNext": "Następny rząd",
            "rowPrevious": "Poprzedni wiersz",
            "rowRendered": "Renderowane wiersze",
            "rowRows": "Wydziwianie",
            "rowSelected": "Wybrane wiersze",
            "rowTotal": "Łączna liczba wierszy",
            "searchFrom": "Z",
            "searchSearch": "Szukaj",
            "searchTo": "Do",
            "totalsAverage": "Średni",
            "totalsCalculate": "Oblicz",
            "totalsCancel": "Anuluj",
            "totalsCount": "Liczyć",
            "totalsDifference": "Różnica",
            "totalsDistinct": "Odrębny",
            "totalsFormula": "Formuła",
            "totalsMinimum": "Minimo",
            "totalsMaximum": "Maksymalny",
            "totalsProduct": "Iloczyn",
            "totalsSum": "Suma"
        }
    },
    "russian": {
        "keys": {
            "checkboxAll": "Все",
            "checkboxChecked": "Проверено",
            "checkboxIndeterminate": "Неопределенный",
            "checkboxUnchecked": "Не отмечено",
            "columnAdd": "Добавить столбец",
            "columnAddDescription": "Добавить столбец кода / описания",
            "columnColumns": "Столбцы",
            "columnHide": "Скрыть столбец",
            "columnMerge": "Объединить столбцы",
            "columnNoFormula": "Для этих столбцов нет доступных формул",
            "columnNonNumerical": "Эти столбцы не числовые",
            "columnNonNumericalInTable": "В этой таблице нет числовых столбцов",
            "columnSwap": "Поменять местами столбцы",
            "dashboardDimension": "Измерение",
            "dashboardLoaded": "Загружено",
            "dashboardReset": "Перезагрузить",
            "dashboardSave": "Сохранять",
            "dashboardVertical": "Вертикальный",
            "debugAutoprint": "Включить автоматическую печать",
            "debugClear": "Очистить виджет",
            "debugDLAll": "Все",
            "debugDLProps": "Загрузить свойства компонентов",
            "debugDLPropsComp": "Скачать реквизиты компонентов",
            "debugDump": "Дамп сохраненных журналов",
            "debugLanguageChanger": "Установить язык",
            "debugLocaleChanger": "Установить языковой стандарт",
            "debugLogLimit": "Установить ограничение журнала",
            "debugMagicBox": "Переключить волшебный ящик купа",
            "debugOff": "Отключить отладку",
            "debugPrint": "Печать сохраненных журналов",
            "debugThemeChanger": "Установить тему",
            "densityDense": "Плотный",
            "densityLabel": "Плотность строк",
            "densityMedium": "Середина",
            "densityWide": "Широкий",
            "fontsizeBig": "Большой",
            "fontsizeLabel": "Размер шрифта",
            "fontsizeMedium": "Середина",
            "fontsizeSmall": "Небольшой",
            "genericAbort": "Отмена",
            "genericAddNew": "Добавить новое",
            "genericApply": "Применять",
            "genericBack": "назад",
            "genericCollapse": "Kpax",
            "genericConfirm": "Подтверждать",
            "genericConfirmDelete": "вы подтверждаете отмену?",
            "genericConfirmDeleteXRows": "Удалить ({0}) строки?",
            "genericDay": "День",
            "genericDragAndDrop": "Перетащить и отпустить",
            "genericDropYourData": "Перетащите сюда свои данные",
            "genericEditable": "Редактируемый",
            "genericEditableField": "Это поле можно редактировать",
            "genericEmptyData": "Пустые данные",
            "genericEmptyObject": "Пустые объект",
            "genericExpand": "Расширять",
            "genericExperimentalFeat": "Экспериментальная особенность",
            "genericFilters": "Фильтры",
            "genericInfo": "Информация",
            "genericInvalidColor": "Неверный цвет",
            "genericLayoutNotYetImplemented": "Макет еще не реализован",
            "genericList": "Список",
            "genericLoadMoreData": "Загрузить больше данных",
            "genericMenu": "Меню",
            "genericMerge": "Объединить",
            "genericMonth": "Месяц",
            "genericMove": "Переехать",
            "genericNext": "Следующий",
            "genericNo": "Нет",
            "genericOpenInNewTab": "Открыть в новой вкладке",
            "genericOpenInNewWindow": "Открыть в новом окне",
            "genericOpenNavigationMenu": "Открыть меню навигации",
            "genericOptions": "Параметры",
            "genericPrevious": "Предыдущий",
            "genericRemoveFilters": "Удалить фильтры",
            "genericSettings": "Настройки",
            "genericShowRowOptions": "Показать параметры строки",
            "genericShowTooltipInfo": "Показать информацию во всплывающей подсказке",
            "genericSortBy": "Сортировать по",
            "genericSwap": "Менять",
            "genericToday": "Сегодня",
            "genericToggle": "Переключать",
            "genericTop": "Вершина",
            "genericTotalsTable": "Итоговая таблица",
            "genericTransposeData": "Транспонировать данные",
            "genericViewAs": "Просмотреть как",
            "genericWeek": "Неделя",
            "genericYes": "Да",
            "gridColumn": "Столбец",
            "gridComplete": "Полный",
            "gridLabel": "Тип сетки",
            "gridNone": "Никто",
            "gridRow": "Строка",
            "groupingDisable": "Отключить группировку",
            "groupingEnable": "Включить группировку",
            "groupingGroups": "Группы",
            "pagePage": "Страница",
            "pageTotal": "Всего страниц",
            "rowDetail": "Детали строки",
            "rowEditableKey": "Редактируемый ключ записи",
            "rowKey": "Ключ записи",
            "rowNext": "Следующая строка",
            "rowPrevious": "Предыдущая строка",
            "rowRendered": "Отрисованные строки",
            "rowRows": "Рядов",
            "rowSelected": "Выбранные строки",
            "rowTotal": "Всего строк",
            "searchFrom": "Из",
            "searchSearch": "Поиск",
            "searchTo": "К",
            "totalsAverage": "В среднем",
            "totalsCalculate": "Рассчитать",
            "totalsCancel": "Отмена",
            "totalsCount": "Считать",
            "totalsDifference": "Разница",
            "totalsDistinct": "Отчетливый",
            "totalsFormula": "Формула",
            "totalsMinimum": "Минимум",
            "totalsMaximum": "Максимум",
            "totalsProduct": "Продукт",
            "totalsSum": "Сумма"
        }
    },
    "spanish": {
        "keys": {
            "checkboxAll": "Todas",
            "checkboxChecked": "Marcado",
            "checkboxIndeterminate": "Indeterminado",
            "checkboxUnchecked": "Sin marcar",
            "columnAdd": "Añadir columna",
            "columnAddDescription": "Agregar columna de código / descripción",
            "columnColumns": "Columnas",
            "columnHide": "Ocultar columna",
            "columnMerge": "Fusionar columnas",
            "columnNoFormula": "No hay fórmulas disponibles para estas columnas.",
            "columnNonNumerical": "Estas columnas no son numéricas.",
            "columnNonNumericalInTable": "No existen columnas numéricas en esta tabla.",
            "columnSwap": "Intercambiar columnas",
            "dashboardDimension": "Dimensión",
            "dashboardLoaded": "Cargado",
            "dashboardReset": "Reiniciar",
            "dashboardSave": "Ahorrar",
            "dashboardVertical": "Vertical",
            "debugAutoprint": "Alternar impresión automática",
            "debugClear": "Borrar widget",
            "debugDLAll": "Todas",
            "debugDLProps": "Descargar accesorios de componentes",
            "debugDLPropsComp": "Descargar accesorios de componentes",
            "debugDump": "Volcar registros almacenados",
            "debugLanguageChanger": "Establecer idioma",
            "debugLocaleChanger": "Establecer configuración regional",
            "debugLogLimit": "Establecer límite de registro",
            "debugMagicBox": "Alternar kup-magic-box",
            "debugOff": "Desactivar depuración",
            "debugPrint": "Imprimir registros almacenados",
            "debugThemeChanger": "Establecer tema",
            "densityDense": "Densa",
            "densityLabel": "Densidad de hileras",
            "densityMedium": "Medio",
            "densityWide": "Amplia",
            "fontsizeBig": "Grande",
            "fontsizeLabel": "Tamaño de fuente",
            "fontsizeMedium": "Medio",
            "fontsizeSmall": "Pequeño",
            "genericAbort": "Cancelar",
            "genericAddNew": "Añadir nuevo",
            "genericApply": "Solicitar",
            "genericBack": "Espalda",
            "genericCollapse": "Colapso",
            "genericConfirm": "Confirmar",
            "genericConfirmDelete": "¿Confirmas la cancelación?",
            "genericConfirmDeleteXRows": "¿Eliminar ({0}) filas?",
            "genericDay": "Día",
            "genericDragAndDrop": "Arrastrar y soltar",
            "genericDropYourData": "Deja tus datos aquí",
            "genericEditable": "Editable",
            "genericEditableField": "Este campo se puede editar",
            "genericEmptyData": "Datos vacíos",
            "genericEmptyObject": "Objeto vacíos",
            "genericExpand": "Expandir",
            "genericExperimentalFeat": "Característica experimental",
            "genericFilters": "Filtros",
            "genericInfo": "Información",
            "genericInvalidColor": "Color inválido",
            "genericLayoutNotYetImplemented": "Diseño aún no implementado",
            "genericList": "Lista",
            "genericLoadMoreData": "Cargar más datos",
            "genericMenu": "Menú",
            "genericMerge": "Unir",
            "genericMonth": "Mes",
            "genericMove": "Mover",
            "genericNext": "Próximo",
            "genericNo": "No",
            "genericOpenInNewTab": "Abrir en una pestaña nueva",
            "genericOpenInNewWindow": "Abrir en Nueva ventana",
            "genericOpenNavigationMenu": "Abrir menú de navegación",
            "genericOptions": "Opciones",
            "genericPrevious": "Previo",
            "genericRemoveFilters": "Quitar filtros",
            "genericSettings": "Ajustes",
            "genericShowRowOptions": "Mostrar opciones de fila",
            "genericShowTooltipInfo": "Mostrar información de información sobre herramientas",
            "genericSortBy": "Ordenar por",
            "genericSwap": "Intercambio",
            "genericToday": "Hoy dia",
            "genericToggle": "Palanca",
            "genericTop": "Cima",
            "genericTotalsTable": "Tabla de totales",
            "genericTransposeData": "Transponer datos",
            "genericViewAs": "Visto como",
            "genericWeek": "Semana",
            "genericYes": "Sí",
            "gridColumn": "Columna",
            "gridComplete": "Completa",
            "gridLabel": "Tipo de cuadrícula",
            "gridNone": "Ninguna",
            "gridRow": "Fila",
            "groupingDisable": "Desactivar agrupación",
            "groupingEnable": "Habilitar agrupación",
            "groupingGroups": "Grupo",
            "pagePage": "Página",
            "pageTotal": "Paginas totales",
            "rowDetail": "Detalle de fila",
            "rowEditableKey": "Clave de registro editable",
            "rowKey": "Grabar clave",
            "rowNext": "Siguiente fila",
            "rowPrevious": "Fila anterior",
            "rowRendered": "Filas renderizadas",
            "rowRows": "Filas",
            "rowSelected": "Filas seleccionadas",
            "rowTotal": "Filas totales",
            "searchFrom": "De",
            "searchSearch": "Buscar",
            "searchTo": "A",
            "totalsAverage": "Promedio",
            "totalsCalculate": "Calcular",
            "totalsCancel": "Cancelar",
            "totalsCount": "Contar",
            "totalsDifference": "Diferencia",
            "totalsDistinct": "Distinct",
            "totalsFormula": "Fórmula",
            "totalsMaximum": "Máximo",
            "totalsMinimum": "Mínimo",
            "totalsProduct": "Producto",
            "totalsSum": "Suma"
        }
    }
}
